stimpy/__init__.py
stimpy/animate/__init__.py
stimpy/animate/_animate.py
stimpy/animate/_func.py
stimpy/animate/opacity.py
stimpy/animate/ori.py
stimpy/animate/phase.py
stimpy/animate/pos.py
stimpy/animate/size.py
stimpy/scene.py
stimpy/stim.py
stimpy/trial.py
stimpy/visual.py
stimpy/window.py
stimpy-0.3.0.dist-info/LICENSE
stimpy-0.3.0.dist-info/WHEEL
stimpy-0.3.0.dist-info/METADATA
stimpy-0.3.0.dist-info/RECORD
