Metadata-Version: 2.1
Name: stimpy
Version: 0.3.0
Summary: A PsychoPy wrapper to create moving visual stimuli without loops.
Home-page: https://github.com/kclamar/stimpy
License: MIT
Author: Ka Chung Lam
Author-email: kclamar@connect.ust.hk
Requires-Python: >=3.8,<4.0
Classifier: Intended Audience :: Science/Research
Classifier: License :: OSI Approved :: MIT License
Classifier: Operating System :: Microsoft :: Windows
Classifier: Programming Language :: Python :: 3
Classifier: Programming Language :: Python :: 3.8
Classifier: Programming Language :: Python :: 3.9
Provides-Extra: dev
Requires-Dist: LabJackPython (>=2.0.4,<3.0.0)
Requires-Dist: PsychoPy (>=2021.2.0,<2022.0.0)
Requires-Dist: black; extra == "dev"
Requires-Dist: flake8; extra == "dev"
Requires-Dist: isort; extra == "dev"
Requires-Dist: mypy; extra == "dev"
Requires-Dist: numpy (>=1.21.0,<2.0.0)
Requires-Dist: pydata-sphinx-theme; extra == "dev"
Requires-Dist: sphinx-autodoc-typehints; extra == "dev"
Requires-Dist: sphinx; extra == "dev"
Project-URL: Repository, https://github.com/kclamar/stimpy
